transport_frames/__init__.py
transport_frames/frame_grader/__init__.py
transport_frames/frame_grader/advanced_grade.py
transport_frames/framebuilder/__init__.py
transport_frames/framebuilder/frame.py
transport_frames/graphbuilder/__init__.py
transport_frames/graphbuilder/graph.py
transport_frames/graphbuilder/road_classifier.py
transport_frames/indicators/__init__.py
transport_frames/indicators/indicator_area.py
transport_frames/indicators/indicator_terr.py
transport_frames/indicators/utils.py
transport_frames/models/__init__.py
transport_frames/models/graph_validation.py
transport_frames/models/polygon_validation.py
transport_frames/models/schema.py
transport_frames/road_adder/__init__.py
transport_frames/road_adder/road_adder.py
transport_frames/transport_provision/transport_provision.py
transport_frames/utils/__init__.py
transport_frames/utils/adj_calc.py
transport_frames/utils/constant_osm_tags.py
transport_frames/utils/constant_road_vars.py
transport_frames/utils/helper_funcs.py
transport_frames_legacy-0.1.2.dist-info/licenses/LICENSE
transport_frames_legacy-0.1.2.dist-info/METADATA
transport_frames_legacy-0.1.2.dist-info/WHEEL
transport_frames_legacy-0.1.2.dist-info/top_level.txt
transport_frames_legacy-0.1.2.dist-info/RECORD
